CHANGES.md
LICENSE.md
MANIFEST.in
README.md
VERSION
pyproject.toml
requirements-ci.txt
requirements-docs-ci.txt
requirements-docs.txt
requirements.txt
setup.py
bin/plot_profile.ipynb
bin/radical-pilot-agent-statepush
bin/radical-pilot-agent_0
bin/radical-pilot-agent_n
bin/radical-pilot-bridge
bin/radical-pilot-command
bin/radical-pilot-component
bin/radical-pilot-control
bin/radical-pilot-create-static-ve
bin/radical-pilot-deploy-ompi.sh
bin/radical-pilot-dragon-executor.py
bin/radical-pilot-hello.sh
bin/radical-pilot-http-balancer
bin/radical-pilot-limits.py
bin/radical-pilot-proxy-server
bin/radical-pilot-prte2prof
bin/radical-pilot-raptor-master
bin/radical-pilot-raptor-worker
bin/radical-pilot-resources
bin/radical-pilot-run-session
bin/radical-pilot-service-wrapper
bin/radical-pilot-stats
bin/radical-pilot-stats.plot
bin/radical-pilot-test-slurm
bin/radical-pilot-ve
bin/radical-pilot-version
docs/source/README.md
docs/source/internals.rst
docs/source/release_notes.md
examples/00_getting_started.py
examples/01_task_details.py
examples/02_failing_tasks.py
examples/03_multiple_pilots.py
examples/04_scheduler_selection.py
examples/05_task_input_data.py
examples/06_task_output_data.py
examples/07_shared_task_data.py
examples/08_task_environment.py
examples/09_mpi_tasks.py
examples/09_mpi_tasks.sh
examples/10_pre_and_post_exec.py
examples/11_task_input_data_tar.py
examples/11_task_input_folder.py
examples/12_task_env.py
examples/agent_services.py
examples/config.json
examples/error_handling.py
examples/helloworld_mpi.py
examples/helloworld_threads.py
examples/lm_task.sh
examples/make_folders.py
examples/rp_analytics.py
examples/data_staging/io_staging_all.py
examples/data_staging/io_staging_dict.py
examples/data_staging/io_staging_pipeline.py
examples/data_staging/io_staging_shared.py
examples/data_staging/io_staging_simple.py
examples/docs/chained_tasks.py
examples/docs/coupled_tasks.py
examples/docs/mpi_tasks.py
examples/docs/simple_bot.py
src/radical.pilot.egg-info/PKG-INFO
src/radical.pilot.egg-info/SOURCES.txt
src/radical.pilot.egg-info/dependency_links.txt
src/radical.pilot.egg-info/not-zip-safe
src/radical.pilot.egg-info/requires.txt
src/radical.pilot.egg-info/top_level.txt
