Metadata-Version: 2.4
Name: radical.pilot
Version: 1.103.0
Summary: RADICAL-Cybertools Pilot Job Framework
Home-page: http://radical-cybertools.github.io/radical.pilot/
Author: RADICAL Group at Rutgers University
Author-email: radical@rutgers.edu
Maintainer: The RADICAL Group
Maintainer-email: radical@rutgers.edu
License: MIT
Project-URL: Documentation, https://radicalpilot.readthedocs.io/en/latest/
Project-URL: Source, https://github.com/radical-cybertools/radical.pilot/
Project-URL: Issues, https://github.com/radical-cybertools/radical.pilot/issues
Keywords: radical,cybertools,pilot job
Classifier: Development Status :: 5 - Production/Stable
Classifier: Intended Audience :: Developers
Classifier: Environment :: Console
Classifier: License :: OSI Approved :: MIT License
Classifier: Programming Language :: Python
Classifier: Programming Language :: Python :: 3
Classifier: Programming Language :: Python :: 3.8
Classifier: Topic :: Utilities
Classifier: Topic :: System :: Distributed Computing
Classifier: Topic :: Scientific/Engineering
Classifier: Operating System :: POSIX
Classifier: Operating System :: Unix
Requires-Python: >=3.8
License-File: LICENSE.md
Requires-Dist: radical.utils<1.110,>=1.100.0
Requires-Dist: radical.gtod<1.110,>=1.100.0
Requires-Dist: psij-python
Requires-Dist: rc.process
Requires-Dist: setproctitle
Requires-Dist: requests
Requires-Dist: cffi
Requires-Dist: dill
Requires-Dist: rc.process
Dynamic: author
Dynamic: author-email
Dynamic: classifier
Dynamic: description
Dynamic: description-content-type
Dynamic: home-page
Dynamic: keywords
Dynamic: license
Dynamic: license-file
Dynamic: maintainer
Dynamic: maintainer-email
Dynamic: project-url
Dynamic: requires-dist
Dynamic: requires-python
Dynamic: summary
